influxdbDataProcessor/__init__.py
influxdbDataProcessor/processor.py
influxdb_data_processor-0.0.4.dist-info/LICENSE
influxdb_data_processor-0.0.4.dist-info/METADATA
influxdb_data_processor-0.0.4.dist-info/WHEEL
influxdb_data_processor-0.0.4.dist-info/top_level.txt
influxdb_data_processor-0.0.4.dist-info/RECORD
