Metadata-Version: 2.1
Name: influxdb-data-processor
Version: 0.0.4
Summary: A data processor for data in influxDB
Home-page: UNKNOWN
Author: Pikacent (Chai Wen Xuan)
Author-email: <vicentchai@hotmail.com>
License: UNKNOWN
Keywords: python,video,stream,video stream,camera stream,sockets
Platform: UNKNOWN
Classifier: Development Status :: 1 - Planning
Classifier: Intended Audience :: Developers
Classifier: Programming Language :: Python :: 3
Classifier: Operating System :: Unix
Classifier: Operating System :: MacOS :: MacOS X
Classifier: Operating System :: Microsoft :: Windows
Requires-Dist: influxdb-client
Requires-Dist: pandas
Requires-Dist: numpy
Requires-Dist: scipy
